rhs_flashkit/__init__.py
rhs_flashkit/constants.py
rhs_flashkit/flashing.py
rhs_flashkit/jlink_programmer.py
rhs_flashkit/programmer.py
rhs_flashkit-0.1.1.dist-info/licenses/LICENSE
rhs_flashkit-0.1.1.dist-info/METADATA
rhs_flashkit-0.1.1.dist-info/WHEEL
rhs_flashkit-0.1.1.dist-info/entry_points.txt
rhs_flashkit-0.1.1.dist-info/top_level.txt
rhs_flashkit-0.1.1.dist-info/RECORD
