Metadata-Version: 2.4
Name: rhs-flashkit
Version: 0.1.1
Summary: CI/CD toolkit for flashing and testing embedded devices
Author-email: Robotics Hardware Solutions <info@rhs.com>
License: MIT
Project-URL: Homepage, https://github.com/RoboticsHardwareSolutions/rhs-flashkit
Project-URL: Repository, https://github.com/RoboticsHardwareSolutions/rhs-flashkit
Project-URL: Bug Tracker, https://github.com/RoboticsHardwareSolutions/rhs-flashkit/issues
Project-URL: Documentation, https://github.com/RoboticsHardwareSolutions/rhs-flashkit#readme
Keywords: embedded,firmware,flashing,jlink,stm32,ci-cd,testing
Classifier: Development Status :: 3 - Alpha
Classifier: Intended Audience :: Developers
Classifier: License :: OSI Approved :: MIT License
Classifier: Programming Language :: Python :: 3
Classifier: Programming Language :: Python :: 3.8
Classifier: Programming Language :: Python :: 3.9
Classifier: Programming Language :: Python :: 3.10
Classifier: Programming Language :: Python :: 3.11
Classifier: Programming Language :: Python :: 3.12
Requires-Python: >=3.8
License-File: LICENSE
Requires-Dist: pylink-square>=1.0.0
Provides-Extra: dev
Requires-Dist: pytest>=7.0; extra == "dev"
Requires-Dist: pytest-cov>=4.0; extra == "dev"
Dynamic: license-file
